file_combiner/__init__.py
file_combiner/file_combiner.py
file_combiner-0.0.2.dist-info/LICENSE
file_combiner-0.0.2.dist-info/METADATA
file_combiner-0.0.2.dist-info/WHEEL
file_combiner-0.0.2.dist-info/top_level.txt
file_combiner-0.0.2.dist-info/RECORD
